odoo/addons/sale_force_invoiced/README.rst
odoo/addons/sale_force_invoiced/__init__.py
odoo/addons/sale_force_invoiced/__manifest__.py
odoo/addons/sale_force_invoiced/i18n/ca.po
odoo/addons/sale_force_invoiced/i18n/de.po
odoo/addons/sale_force_invoiced/i18n/el_GR.po
odoo/addons/sale_force_invoiced/i18n/es.po
odoo/addons/sale_force_invoiced/i18n/es_ES.po
odoo/addons/sale_force_invoiced/i18n/es_VE.po
odoo/addons/sale_force_invoiced/i18n/fi.po
odoo/addons/sale_force_invoiced/i18n/fr.po
odoo/addons/sale_force_invoiced/i18n/hr.po
odoo/addons/sale_force_invoiced/i18n/hr_HR.po
odoo/addons/sale_force_invoiced/i18n/hu.po
odoo/addons/sale_force_invoiced/i18n/it.po
odoo/addons/sale_force_invoiced/i18n/nl.po
odoo/addons/sale_force_invoiced/i18n/nl_NL.po
odoo/addons/sale_force_invoiced/i18n/pt.po
odoo/addons/sale_force_invoiced/i18n/pt_BR.po
odoo/addons/sale_force_invoiced/i18n/ro.po
odoo/addons/sale_force_invoiced/i18n/sale_force_invoiced.pot
odoo/addons/sale_force_invoiced/i18n/sk.po
odoo/addons/sale_force_invoiced/i18n/sl.po
odoo/addons/sale_force_invoiced/i18n/tr.po
odoo/addons/sale_force_invoiced/i18n/tr_TR.po
odoo/addons/sale_force_invoiced/i18n/vi_VN.po
odoo/addons/sale_force_invoiced/i18n/zh_CN.po
odoo/addons/sale_force_invoiced/model/__init__.py
odoo/addons/sale_force_invoiced/model/sale_order.py
odoo/addons/sale_force_invoiced/static/description/icon.png
odoo/addons/sale_force_invoiced/tests/__init__.py
odoo/addons/sale_force_invoiced/tests/test_sale_force_invoiced.py
odoo/addons/sale_force_invoiced/view/sale_view.xml
odoo11_addon_sale_force_invoiced-11.0.1.0.1.dist-info/METADATA
odoo11_addon_sale_force_invoiced-11.0.1.0.1.dist-info/RECORD
odoo11_addon_sale_force_invoiced-11.0.1.0.1.dist-info/WHEEL
odoo11_addon_sale_force_invoiced-11.0.1.0.1.dist-info/top_level.txt
